mmseg/__init__.py
mmseg/version.py
mmseg/.mim/model-index.yml
mmseg/.mim/configs/PP-Liteseg/pp-liteseg_cityscapes_160k.py
mmseg/.mim/configs/PP-Liteseg/pp-liteseg_voc_80k.py
mmseg/.mim/configs/_base_/default_runtime.py
mmseg/.mim/configs/_base_/datasets/ade20k.py
mmseg/.mim/configs/_base_/datasets/ade20k_640x640.py
mmseg/.mim/configs/_base_/datasets/chase_db1.py
mmseg/.mim/configs/_base_/datasets/cityscapes.py
mmseg/.mim/configs/_base_/datasets/cityscapes_1024x1024.py
mmseg/.mim/configs/_base_/datasets/cityscapes_768x768.py
mmseg/.mim/configs/_base_/datasets/cityscapes_769x769.py
mmseg/.mim/configs/_base_/datasets/cityscapes_832x832.py
mmseg/.mim/configs/_base_/datasets/coco-stuff10k.py
mmseg/.mim/configs/_base_/datasets/coco-stuff164k.py
mmseg/.mim/configs/_base_/datasets/drive.py
mmseg/.mim/configs/_base_/datasets/hrf.py
mmseg/.mim/configs/_base_/datasets/isaid.py
mmseg/.mim/configs/_base_/datasets/loveda.py
mmseg/.mim/configs/_base_/datasets/pascal_context.py
mmseg/.mim/configs/_base_/datasets/pascal_context_59.py
mmseg/.mim/configs/_base_/datasets/pascal_voc12.py
mmseg/.mim/configs/_base_/datasets/pascal_voc12_aug.py
mmseg/.mim/configs/_base_/datasets/potsdam.py
mmseg/.mim/configs/_base_/datasets/stare.py
mmseg/.mim/configs/_base_/datasets/vaihingen.py
mmseg/.mim/configs/_base_/models/ann_r50-d8.py
mmseg/.mim/configs/_base_/models/apcnet_r50-d8.py
mmseg/.mim/configs/_base_/models/bisenet_liteaspp.py
mmseg/.mim/configs/_base_/models/bisenet_liteaspp_cross_se.py
mmseg/.mim/configs/_base_/models/bisenetv1_r18-d32.py
mmseg/.mim/configs/_base_/models/bisenetv2.py
mmseg/.mim/configs/_base_/models/ccnet_r50-d8.py
mmseg/.mim/configs/_base_/models/cgnet.py
mmseg/.mim/configs/_base_/models/danet_r50-d8.py
mmseg/.mim/configs/_base_/models/deeplabv3_r50-d8.py
mmseg/.mim/configs/_base_/models/deeplabv3_unet_s5-d16.py
mmseg/.mim/configs/_base_/models/deeplabv3plus_r50-d8.py
mmseg/.mim/configs/_base_/models/dmnet_r50-d8.py
mmseg/.mim/configs/_base_/models/dnl_r50-d8.py
mmsegmentation_zzb-0.23.0.dist-info/LICENSE
mmsegmentation_zzb-0.23.0.dist-info/METADATA
mmsegmentation_zzb-0.23.0.dist-info/WHEEL
mmsegmentation_zzb-0.23.0.dist-info/top_level.txt
mmsegmentation_zzb-0.23.0.dist-info/RECORD
