Metadata-Version: 2.1
Name: mmsegmentation-zzb
Version: 0.23.0
Summary: Open MMLab Semantic Segmentation Toolbox and Benchmark
Home-page: http://github.com/open-mmlab/mmsegmentation
Author: MMSegmentation Contributors
Author-email: openmmlab@gmail.com
License: Apache License 2.0
Keywords: computer vision,semantic segmentation
Classifier: Development Status :: 4 - Beta
Classifier: License :: OSI Approved :: Apache Software License
Classifier: Operating System :: OS Independent
Classifier: Programming Language :: Python :: 3.6
Classifier: Programming Language :: Python :: 3.7
Classifier: Programming Language :: Python :: 3.8
Classifier: Programming Language :: Python :: 3.9
License-File: LICENSE
Requires-Dist: matplotlib
Requires-Dist: mmcls (>=0.20.1)
Requires-Dist: numpy
Requires-Dist: packaging
Requires-Dist: prettytable
Provides-Extra: all
Requires-Dist: cityscapesscripts ; extra == 'all'
Requires-Dist: matplotlib ; extra == 'all'
Requires-Dist: mmcls (>=0.20.1) ; extra == 'all'
Requires-Dist: numpy ; extra == 'all'
Requires-Dist: packaging ; extra == 'all'
Requires-Dist: prettytable ; extra == 'all'
Requires-Dist: codecov ; extra == 'all'
Requires-Dist: flake8 ; extra == 'all'
Requires-Dist: interrogate ; extra == 'all'
Requires-Dist: pytest ; extra == 'all'
Requires-Dist: xdoctest (>=0.10.0) ; extra == 'all'
Requires-Dist: yapf ; extra == 'all'
Provides-Extra: build
Provides-Extra: optional
Requires-Dist: cityscapesscripts ; extra == 'optional'
Provides-Extra: tests
Requires-Dist: codecov ; extra == 'tests'
Requires-Dist: flake8 ; extra == 'tests'
Requires-Dist: interrogate ; extra == 'tests'
Requires-Dist: pytest ; extra == 'tests'
Requires-Dist: xdoctest (>=0.10.0) ; extra == 'tests'
Requires-Dist: yapf ; extra == 'tests'
